README
setup.cfg
setup.py
argparse_tools/__init__.py
argparse_tools.egg-info/PKG-INFO
argparse_tools.egg-info/SOURCES.txt
argparse_tools.egg-info/dependency_links.txt
argparse_tools.egg-info/requires.txt
argparse_tools.egg-info/top_level.txt
argparse_tools/examples/__init__.py
argparse_tools/examples/runthat.py
argparse_tools/examples/runthis.py
argparse_tools/examples/shared.py
argparse_tools/examples/simple_subparsers_example.py