Metadata-Version: 1.0
Name: argparse-tools
Version: 1.0.5
Summary: Share a standardized set of argparse arguments within your codebase
Home-page: https://github.com/adgaudio/argparse_tools
Author: Alex Gaudio
Author-email: adgaudio@gmail.com
License: UNKNOWN
Keywords: argparse
Platform: UNKNOWN
